code_animate/__init__.py
code_animate/animate.py
code_animate/helpers/animate_helper.py
code_animate/helpers/frame_helper.py
code_animate/helpers/func_helper.py
code_animate/helpers/models.py
code_animate/helpers/string_helper.py
code_animate-0.0.10.dist-info/METADATA
code_animate-0.0.10.dist-info/WHEEL
code_animate-0.0.10.dist-info/licenses/LICENSE
code_animate-0.0.10.dist-info/RECORD
