Metadata-Version: 2.4
Name: code_animate
Version: 0.0.10
Summary: A package to animate your function call step by step in terminal
Project-URL: Homepage, https://github.com/zlliu246/code_animate
Project-URL: Issues, https://github.com/zlliu246/code_animate/issues
Author-email: Liu Zuo Lin <zlliu246@gmail.com>
License-File: LICENSE
Classifier: License :: OSI Approved :: MIT License
Classifier: Operating System :: OS Independent
Classifier: Programming Language :: Python :: 3
Requires-Python: >=3.8
Requires-Dist: colorama
Requires-Dist: default-deepcopy
Requires-Dist: unprint
